xctools_kamaalio/__init__.py
xctools_kamaalio/cli.py
xctools_kamaalio/project_updater.py
xctools_kamaalio/xctools.py
xctools_kamaalio/actions/acknowledgments.py
xctools_kamaalio/actions/archive.py
xctools_kamaalio/actions/build.py
xctools_kamaalio/actions/bump_version.py
xctools_kamaalio/actions/export_archive.py
xctools_kamaalio/actions/test.py
xctools_kamaalio/actions/trust_swift_macros.py
xctools_kamaalio/actions/trust_swift_plugins.py
xctools_kamaalio/actions/upload.py
xctools_kamaalio-0.5.1.dist-info/licenses/LICENSE
xctools_kamaalio-0.5.1.dist-info/METADATA
xctools_kamaalio-0.5.1.dist-info/WHEEL
xctools_kamaalio-0.5.1.dist-info/entry_points.txt
xctools_kamaalio-0.5.1.dist-info/top_level.txt
xctools_kamaalio-0.5.1.dist-info/RECORD
