Metadata-Version: 2.4
Name: xctools_kamaalio
Version: 0.5.1
Summary: A package to help deal with Xcode projects.
Author-email: Kamaal Farah <kamaal.f1@gmail.com>
License: MIT License
Project-URL: Homepage, https://github.com/Kamaalio/XcTools
Project-URL: Bug Tracker, https://github.com/Kamaalio/XcTools/issues
Classifier: Programming Language :: Python :: 3
Classifier: License :: OSI Approved :: MIT License
Classifier: Operating System :: OS Independent
Requires-Python: >=3.11
License-File: LICENSE
Requires-Dist: click>=8.1.6
Requires-Dist: kamaalpy>=0.1.0
Dynamic: license-file
